[
	{"_id":703448,"name":"Kiev","country":"UA","coord":{"lon":30.516666,"lat":50.433334}},
	{"_id":2643743,"name":"London","country":"GB","coord":{"lon":-0.12574,"lat":51.50853}},
	{"_id":5128638,"name":"New York","country":"US","coord":{"lon":-75.499901,"lat":43.000351}},
	{"_id":2950159,"name":"Berlin","country":"DE","coord":{"lon":13.41053,"lat":52.524368}},
	{"_id":2968815,"name":"Paris","country":"FR","coord":{"lon":2.3486,"lat":48.853401}},
	{"_id":1850147,"name":"Tokyo","country":"JP","coord":{"lon":139.691711,"lat":35.689499}},
	{"_id":3451190,"name":"Rio de Janeiro","country":"BR","coord":{"lon":-43.2075,"lat":-22.902781}},
	{"_id":6359304,"name":"Madrid","country":"ES","coord":{"lon":-3.68275,"lat":40.489349}},
	{"_id":1819729,"name":"Hong Kong","country":"HK","coord":{"lon":114.157692,"lat":22.285521}},
	{"_id":702550,"name":"Lviv","country":"UA","coord":{"lon":24.023239,"lat":49.838261}}
]